pim_video/__init__.py
pim_video/pim_video.py
pim_video-2.0.0.dist-info/LICENSE
pim_video-2.0.0.dist-info/METADATA
pim_video-2.0.0.dist-info/WHEEL
pim_video-2.0.0.dist-info/entry_points.txt
pim_video-2.0.0.dist-info/top_level.txt
pim_video-2.0.0.dist-info/RECORD
