Metadata-Version: 2.1
Name: pim-video
Version: 2.0.0
Summary: pim videos merging program
Home-page: https://github.com/jtur044/pim_video
Author: Zaw Lin Tun
Author-email: zawlintun1511@gmail.com
License: Apache Software
Keywords: pim videos merging program pim_video
Classifier: Programming Language :: Python :: 3
Classifier: License :: OSI Approved :: Apache Software License
Classifier: Operating System :: OS Independent
License-File: LICENSE
Requires-Dist: setuptools
